[
  {
    "name": "2001v",
    "z": 0.016,
    "d": 186.83316655407606,
    "t": 186
  },
  {
    "name": "2001cn",
    "z": 0.0154363,
    "d": 197.22542460241976,
    "t": 196
  },
  {
    "name": "2005bo",
    "z": 0.0150270427632,
    "d": 198.14658522532224,
    "t": 197
  },
  {
    "name": "1998ef",
    "z": 0.016743,
    "d": 202.6563770236858,
    "t": 202
  },
  {
    "name": "1996bo",
    "z": 0.016321,
    "d": 204.11702426149762,
    "t": 203
  },
  {
    "name": "2001bf",
    "z": 0.0152,
    "d": 204.29378537289887,
    "t": 203
  },
  {
    "name": "2001cz",
    "z": 0.016345641,
    "d": 206.62840868279702,
    "t": 206
  },
  {
    "name": "1994s",
    "z": 0.015166,
    "d": 212.4330888811307,
    "t": 211
  },
  {
    "name": "2007s",
    "z": 0.015,
    "d": 213.4234104276632,
    "t": 212
  },
  {
    "name": "1999aa",
    "z": 0.015,
    "d": 218.60527624652167,
    "t": 217
  },
  {
    "name": "2001da",
    "z": 0.016,
    "d": 219.44984361476722,
    "t": 218
  },
  {
    "name": "2000dk",
    "z": 0.01645,
    "d": 220.08940779402934,
    "t": 219
  },
  {
    "name": "1996bv",
    "z": 0.01673,
    "d": 224.6403155635747,
    "t": 223
  },
  {
    "name": "2006le",
    "z": 0.0173,
    "d": 224.9003178920699,
    "t": 224
  },
  {
    "name": "2001g",
    "z": 0.0173,
    "d": 226.9466728123934,
    "t": 226
  },
  {
    "name": "1998v",
    "z": 0.017173,
    "d": 228.12105565603306,
    "t": 227
  },
  {
    "name": "2002do",
    "z": 0.0152,
    "d": 228.3222600047246,
    "t": 227
  },
  {
    "name": "1999ek",
    "z": 0.017605,
    "d": 236.92223004182117,
    "t": 235
  },
  {
    "name": "1997y",
    "z": 0.016559,
    "d": 237.17017640287946,
    "t": 236
  },
  {
    "name": "2006ax",
    "z": 0.0179312833626,
    "d": 237.50428199665433,
    "t": 236
  },
  {
    "name": "2005a",
    "z": 0.0183152320362,
    "d": 239.8251058228119,
    "t": 238
  },
  {
    "name": "2008l",
    "z": 0.0189,
    "d": 240.01294985290187,
    "t": 238
  },
  {
    "name": "1998co",
    "z": 0.016991,
    "d": 240.91462034187967,
    "t": 239
  },
  {
    "name": "2006td",
    "z": 0.015,
    "d": 241.49849220009833,
    "t": 240
  },
  {
    "name": "2002hw",
    "z": 0.0163,
    "d": 249.49081499523163,
    "t": 248
  },
  {
    "name": "2007ci",
    "z": 0.0192,
    "d": 253.20889415021549,
    "t": 251
  },
  {
    "name": "2007ca",
    "z": 0.0151,
    "d": 258.28080701979025,
    "t": 256
  },
  {
    "name": "1992bc",
    "z": 0.019599,
    "d": 264.2652084159667,
    "t": 262
  },
  {
    "name": "2005ls",
    "z": 0.0205,
    "d": 267.9593463559088,
    "t": 266
  },
  {
    "name": "2005ki",
    "z": 0.0203747245299,
    "d": 272.8694918198974,
    "t": 271
  },
  {
    "name": "2003w",
    "z": 0.0211,
    "d": 273.2129478732512,
    "t": 271
  },
  {
    "name": "1992bo",
    "z": 0.017227,
    "d": 273.4525741166097,
    "t": 271
  },
  {
    "name": "2007au",
    "z": 0.0209,
    "d": 278.626488082182,
    "t": 276
  },
  {
    "name": "2006cm",
    "z": 0.0153,
    "d": 280.71696801364635,
    "t": 278
  },
  {
    "name": "2006ej",
    "z": 0.0192,
    "d": 283.4667863556754,
    "t": 281
  },
  {
    "name": "2002kf",
    "z": 0.0195,
    "d": 286.0362072283747,
    "t": 283
  },
  {
    "name": "2002bf",
    "z": 0.0249,
    "d": 290.72730808417884,
    "t": 288
  },
  {
    "name": "2006kf",
    "z": 0.0208,
    "d": 290.78802423413657,
    "t": 288
  },
  {
    "name": "2006et",
    "z": 0.0212,
    "d": 297.6747551051482,
    "t": 295
  },
  {
    "name": "2007bc",
    "z": 0.0219,
    "d": 297.7252042603741,
    "t": 295
  },
  {
    "name": "1995ak",
    "z": 0.0219800059146,
    "d": 298.2484374526361,
    "t": 295
  },
  {
    "name": "2006cp",
    "z": 0.0233,
    "d": 301.889957071552,
    "t": 299
  },
  {
    "name": "2007cq",
    "z": 0.0247,
    "d": 305.8917289645591,
    "t": 303
  },
  {
    "name": "2001n",
    "z": 0.0221,
    "d": 306.3673416622822,
    "t": 303
  },
  {
    "name": "2004bg",
    "z": 0.0221,
    "d": 307.86359536800444,
    "t": 305
  },
  {
    "name": "2006bq",
    "z": 0.0215,
    "d": 309.5528448036874,
    "t": 306
  },
  {
    "name": "2008bf",
    "z": 0.0251,
    "d": 310.6810174106824,
    "t": 308
  },
  {
    "name": "2001cp",
    "z": 0.0224,
    "d": 311.33109884972936,
    "t": 308
  },
  {
    "name": "1999gd",
    "z": 0.019264,
    "d": 313.0847873006554,
    "t": 310
  },
  {
    "name": "2000bh",
    "z": 0.023953,
    "d": 313.9698587721339,
    "t": 311
  },
  {
    "name": "2000fa",
    "z": 0.021793,
    "d": 315.3699839383101,
    "t": 312
  },
  {
    "name": "2006ac",
    "z": 0.0239,
    "d": 323.7152734101404,
    "t": 320
  },
  {
    "name": "2005bg",
    "z": 0.0241852990802,
    "d": 326.2212309217921,
    "t": 323
  },
  {
    "name": "2000ca",
    "z": 0.024525,
    "d": 326.99226348355256,
    "t": 324
  },
  {
    "name": "2002jy",
    "z": 0.0187,
    "d": 327.3705199404625,
    "t": 324
  },
  {
    "name": "2006sr",
    "z": 0.023,
    "d": 329.36600500824755,
    "t": 326
  },
  {
    "name": "1992ag",
    "z": 0.027342,
    "d": 330.26610156077584,
    "t": 327
  },
  {
    "name": "1998ab",
    "z": 0.027865,
    "d": 331.2573265096393,
    "t": 328
  },
  {
    "name": "2000cn",
    "z": 0.023208,
    "d": 331.5664056415423,
    "t": 328
  },
  {
    "name": "1994m",
    "z": 0.024314,
    "d": 334.8820034731251,
    "t": 331
  },
  {
    "name": "2005m",
    "z": 0.0229711675782,
    "d": 339.1088325984234,
    "t": 335
  },
  {
    "name": "2007qe",
    "z": 0.0229,
    "d": 339.8739980627576,
    "t": 336
  },
  {
    "name": "1998eg",
    "z": 0.023536,
    "d": 344.54234105745934,
    "t": 341
  },
  {
    "name": "2003it",
    "z": 0.024,
    "d": 345.4324271357379,
    "t": 342
  },
  {
    "name": "2007f",
    "z": 0.0242,
    "d": 347.4699485573913,
    "t": 343
  },
  {
    "name": "2006ar",
    "z": 0.0229,
    "d": 349.1131115554576,
    "t": 345
  },
  {
    "name": "2006mp",
    "z": 0.0233,
    "d": 349.2162260567848,
    "t": 345
  },
  {
    "name": "2005na",
    "z": 0.0268091974805,
    "d": 358.0686201262944,
    "t": 354
  },
  {
    "name": "2002he",
    "z": 0.0248,
    "d": 358.1148165930861,
    "t": 354
  },
  {
    "name": "2007co",
    "z": 0.0266,
    "d": 368.74264188430834,
    "t": 364
  },
  {
    "name": "1993ah",
    "z": 0.028488,
    "d": 372.00035519750924,
    "t": 367
  },
  {
    "name": "2003u",
    "z": 0.0261,
    "d": 375.2491997352997,
    "t": 371
  },
  {
    "name": "2004gc",
    "z": 0.0321340168614,
    "d": 376.11044139766966,
    "t": 371
  },
  {
    "name": "1999gp",
    "z": 0.026038,
    "d": 376.4565631687641,
    "t": 372
  },
  {
    "name": "2005mc",
    "z": 0.026,
    "d": 378.9109793684196,
    "t": 374
  },
  {
    "name": "2005ms",
    "z": 0.0259,
    "d": 385.04777049803283,
    "t": 380
  },
  {
    "name": "2004ef",
    "z": 0.029802136901,
    "d": 393.4200219504471,
    "t": 388
  },
  {
    "name": "2004gs",
    "z": 0.0275687259109,
    "d": 395.1021468468914,
    "t": 390
  },
  {
    "name": "1992p",
    "z": 0.026489,
    "d": 396.4684609956866,
    "t": 391
  },
  {
    "name": "2002de",
    "z": 0.0283,
    "d": 403.05105281416326,
    "t": 398
  },
  {
    "name": "1990o",
    "z": 0.030604,
    "d": 407.7384175209859,
    "t": 402
  },
  {
    "name": "2005eq",
    "z": 0.0283960268116,
    "d": 408.2208744481869,
    "t": 403
  },
  {
    "name": "2007bd",
    "z": 0.032,
    "d": 414.42473878804503,
    "t": 409
  },
  {
    "name": "2006qo",
    "z": 0.0308,
    "d": 415.8649699508782,
    "t": 410
  },
  {
    "name": "2001ba",
    "z": 0.030529,
    "d": 417.07564575243447,
    "t": 411
  },
  {
    "name": "2001ie",
    "z": 0.0312,
    "d": 422.1287711111105,
    "t": 416
  },
  {
    "name": "2006bw",
    "z": 0.0308,
    "d": 422.71499770509234,
    "t": 417
  },
  {
    "name": "2002ck",
    "z": 0.0303,
    "d": 422.780038955511,
    "t": 417
  },
  {
    "name": "2006os",
    "z": 0.0321,
    "d": 425.91162449859513,
    "t": 420
  },
  {
    "name": "2006az",
    "z": 0.0315,
    "d": 426.7602306423971,
    "t": 421
  },
  {
    "name": "1996c",
    "z": 0.0275,
    "d": 428.1394590220991,
    "t": 422
  },
  {
    "name": "2002hd",
    "z": 0.036,
    "d": 430.44541469464554,
    "t": 424
  },
  {
    "name": "2003ch",
    "z": 0.0256,
    "d": 435.9054022589826,
    "t": 429
  },
  {
    "name": "2006gj",
    "z": 0.0277,
    "d": 439.09683109900766,
    "t": 432
  },
  {
    "name": "1999cc",
    "z": 0.031528,
    "d": 442.28136280327095,
    "t": 436
  },
  {
    "name": "2006br",
    "z": 0.0255,
    "d": 443.1235866663318,
    "t": 436
  },
  {
    "name": "2008af",
    "z": 0.0341,
    "d": 449.7366903430966,
    "t": 443
  },
  {
    "name": "2006en",
    "z": 0.0308,
    "d": 452.9797042411938,
    "t": 446
  },
  {
    "name": "2007cp",
    "z": 0.0377,
    "d": 453.31174830487436,
    "t": 446
  },
  {
    "name": "2006bt",
    "z": 0.0325,
    "d": 459.36100738990524,
    "t": 452
  },
  {
    "name": "1996bl",
    "z": 0.036,
    "d": 459.4831276627063,
    "t": 452
  },
  {
    "name": "2007ai",
    "z": 0.032,
    "d": 462.4709693161962,
    "t": 455
  },
  {
    "name": "2003kc",
    "z": 0.0341,
    "d": 464.7766553970667,
    "t": 457
  },
  {
    "name": "2003cq",
    "z": 0.0337,
    "d": 465.33964242406336,
    "t": 458
  },
  {
    "name": "2006te",
    "z": 0.0321,
    "d": 471.8201601366913,
    "t": 464
  },
  {
    "name": "2004l",
    "z": 0.0334,
    "d": 473.3098122406996,
    "t": 466
  },
  {
    "name": "2007r",
    "z": 0.0312,
    "d": 474.95745955309695,
    "t": 467
  },
  {
    "name": "2004as",
    "z": 0.0321,
    "d": 477.422674411925,
    "t": 470
  },
  {
    "name": "1992bg",
    "z": 0.03648,
    "d": 477.451620377988,
    "t": 470
  },
  {
    "name": "2006cz",
    "z": 0.0425,
    "d": 479.70053631306774,
    "t": 472
  },
  {
    "name": "2001ay",
    "z": 0.0309,
    "d": 485.4046599215331,
    "t": 477
  },
  {
    "name": "2005eu",
    "z": 0.0341,
    "d": 486.8235007123356,
    "t": 479
  },
  {
    "name": "2006s",
    "z": 0.0329,
    "d": 487.21576898829386,
    "t": 479
  },
  {
    "name": "1994t",
    "z": 0.03572,
    "d": 490.10786326066636,
    "t": 482
  },
  {
    "name": "2007o",
    "z": 0.0366,
    "d": 492.122057599344,
    "t": 484
  },
  {
    "name": "2005iq",
    "z": 0.0329123710881,
    "d": 493.09753260386583,
    "t": 485
  },
  {
    "name": "2006gr",
    "z": 0.0335,
    "d": 494.17632089583725,
    "t": 486
  },
  {
    "name": "2002g",
    "z": 0.0345,
    "d": 494.7027296680786,
    "t": 486
  },
  {
    "name": "1997dg",
    "z": 0.029955,
    "d": 495.517754685291,
    "t": 487
  },
  {
    "name": "2001eh",
    "z": 0.0362,
    "d": 495.85698670192477,
    "t": 487
  },
  {
    "name": "2002hu",
    "z": 0.0292,
    "d": 500.5408009945208,
    "t": 492
  },
  {
    "name": "2003iv",
    "z": 0.0336,
    "d": 501.3630392353436,
    "t": 493
  },
  {
    "name": "2006cc",
    "z": 0.0327,
    "d": 522.7393223318254,
    "t": 513
  },
  {
    "name": "2000cf",
    "z": 0.036457,
    "d": 530.5437967058599,
    "t": 521
  },
  {
    "name": "2006mo",
    "z": 0.036,
    "d": 533.7352934863794,
    "t": 524
  },
  {
    "name": "1992bl",
    "z": 0.042233,
    "d": 579.0992393943102,
    "t": 567
  },
  {
    "name": "1999aw",
    "z": 0.0393,
    "d": 580.1816390015645,
    "t": 568
  },
  {
    "name": "1995ac",
    "z": 0.048818,
    "d": 587.662431769198,
    "t": 576
  },
  {
    "name": "2001az",
    "z": 0.0406,
    "d": 587.8535002549932,
    "t": 576
  },
  {
    "name": "2005lz",
    "z": 0.0402,
    "d": 590.4942474977789,
    "t": 578
  },
  {
    "name": "2005ku",
    "z": 0.0437189114895,
    "d": 591.7735573706683,
    "t": 579
  },
  {
    "name": "2006cf",
    "z": 0.0423,
    "d": 594.2898957021317,
    "t": 582
  },
  {
    "name": "2005hf",
    "z": 0.0421,
    "d": 596.498717815366,
    "t": 584
  },
  {
    "name": "1998dx",
    "z": 0.05371,
    "d": 610.9314775171548,
    "t": 598
  },
  {
    "name": "2004gu",
    "z": 0.0469673346156,
    "d": 619.97683441042,
    "t": 606
  },
  {
    "name": "2005hc",
    "z": 0.0449766726113,
    "d": 637.3799420802458,
    "t": 623
  },
  {
    "name": "1990af",
    "z": 0.049922,
    "d": 639.239440929823,
    "t": 625
  },
  {
    "name": "2003ic",
    "z": 0.0546,
    "d": 649.007687131276,
    "t": 634
  },
  {
    "name": "1992bh",
    "z": 0.045295,
    "d": 664.1122130072133,
    "t": 649
  },
  {
    "name": "2006ot",
    "z": 0.0522,
    "d": 670.1785589172217,
    "t": 654
  },
  {
    "name": "1993ag",
    "z": 0.050043,
    "d": 674.05045138438,
    "t": 658
  },
  {
    "name": "2006eq",
    "z": 0.0483921953954,
    "d": 676.1904021826696,
    "t": 660
  },
  {
    "name": "2006cq",
    "z": 0.0491,
    "d": 689.6618364549868,
    "t": 673
  },
  {
    "name": "1993ac",
    "z": 0.048948,
    "d": 690.2261760248409,
    "t": 673
  },
  {
    "name": "1993o",
    "z": 0.052926,
    "d": 715.4286137637289,
    "t": 697
  },
  {
    "name": "1999ao",
    "z": 0.0544,
    "d": 760.864969930103,
    "t": 740
  },
  {
    "name": "2006py",
    "z": 0.0566833670752,
    "d": 762.4399547683604,
    "t": 742
  },
  {
    "name": "2001ah",
    "z": 0.0583,
    "d": 785.8563054888432,
    "t": 764
  },
  {
    "name": "2006ob",
    "z": 0.0583,
    "d": 795.1970104047274,
    "t": 773
  },
  {
    "name": "2005hj",
    "z": 0.0576,
    "d": 803.8144222627553,
    "t": 781
  },
  {
    "name": "2006oa",
    "z": 0.0589,
    "d": 814.5175742411238,
    "t": 791
  },
  {
    "name": "2005ho",
    "z": 0.0618357646938,
    "d": 819.534898261699,
    "t": 796
  },
  {
    "name": "2007ae",
    "z": 0.0643,
    "d": 834.5690720018055,
    "t": 810
  },
  {
    "name": "2006an",
    "z": 0.0651,
    "d": 885.8775170093396,
    "t": 858
  },
  {
    "name": "2005kt",
    "z": 0.0638640836964,
    "d": 890.6930837990935,
    "t": 863
  },
  {
    "name": "2005if",
    "z": 0.0664403123402,
    "d": 911.8226214417754,
    "t": 882
  },
  {
    "name": "1993b",
    "z": 0.070086,
    "d": 940.4907557848031,
    "t": 909
  },
  {
    "name": "1992bp",
    "z": 0.078577,
    "d": 951.05843571404,
    "t": 919
  },
  {
    "name": "2006on",
    "z": 0.0688,
    "d": 959.0838745015413,
    "t": 926
  },
  {
    "name": "1992bs",
    "z": 0.062668,
    "d": 963.1860235457904,
    "t": 930
  },
  {
    "name": "2006al",
    "z": 0.069,
    "d": 994.6213911011848,
    "t": 960
  },
  {
    "name": "2005ir",
    "z": 0.0753501119815,
    "d": 995.1625025849216,
    "t": 960
  },
  {
    "name": "1992ae",
    "z": 0.074605,
    "d": 999.5400475270612,
    "t": 964
  },
  {
    "name": "1999bp",
    "z": 0.0784,
    "d": 1040.1455523354732,
    "t": 1002
  },
  {
    "name": "2005ag",
    "z": 0.0800481440021,
    "d": 1040.2187004432424,
    "t": 1002
  },
  {
    "name": "2006cj",
    "z": 0.0684,
    "d": 1073.8198366928752,
    "t": 1033
  },
  {
    "name": "2005iu",
    "z": 0.0890194292939,
    "d": 1101.7444272812077,
    "t": 1059
  },
  {
    "name": "2005gb",
    "z": 0.0858546441437,
    "d": 1169.8846320154123,
    "t": 1122
  },
  {
    "name": "2005ed",
    "z": 0.0856961170652,
    "d": 1192.5482581869471,
    "t": 1142
  },
  {
    "name": "2005ff",
    "z": 0.0856894593607,
    "d": 1194.5462374153262,
    "t": 1144
  },
  {
    "name": "2006bu",
    "z": 0.0843,
    "d": 1226.4297342895786,
    "t": 1173
  },
  {
    "name": "2005ex",
    "z": 0.0929368181997,
    "d": 1270.56490860371,
    "t": 1214
  },
  {
    "name": "2005fn",
    "z": 0.0939086318905,
    "d": 1285.3131724188138,
    "t": 1227
  },
  {
    "name": "1992br",
    "z": 0.087589,
    "d": 1326.6993254558065,
    "t": 1265
  },
  {
    "name": "2005je",
    "z": 0.0931494026855,
    "d": 1351.8519383006162,
    "t": 1288
  },
  {
    "name": "1992aq",
    "z": 0.100915,
    "d": 1455.5302473040983,
    "t": 1381
  },
  {
    "name": "2005lk",
    "z": 0.102715033935,
    "d": 1473.7184717353887,
    "t": 1398
  },
  {
    "name": "2005ml",
    "z": 0.113042644637,
    "d": 1503.8514066488272,
    "t": 1425
  },
  {
    "name": "2005fh",
    "z": 0.117625328764,
    "d": 1517.0970744266954,
    "t": 1437
  },
  {
    "name": "2005hn",
    "z": 0.106712340103,
    "d": 1572.9848242439293,
    "t": 1487
  },
  {
    "name": "2005jh",
    "z": 0.108638265524,
    "d": 1580.2874092483082,
    "t": 1493
  },
  {
    "name": "2005kp",
    "z": 0.11471262087,
    "d": 1585.1925033221992,
    "t": 1498
  },
  {
    "name": "2005gp",
    "z": 0.126473161901,
    "d": 1598.817491577709,
    "t": 1510
  },
  {
    "name": "2005ij",
    "z": 0.124273528772,
    "d": 1608.9824232823203,
    "t": 1519
  },
  {
    "name": "2005fv",
    "z": 0.117277362889,
    "d": 1638.5197109977762,
    "t": 1545
  },
  {
    "name": "2005hr",
    "z": 0.116348502599,
    "d": 1640.0373688595923,
    "t": 1547
  },
  {
    "name": "2005hx",
    "z": 0.119671538006,
    "d": 1642.263686134633,
    "t": 1549
  },
  {
    "name": "1999bm",
    "z": 0.1441,
    "d": 1667.9014221167647,
    "t": 1571
  },
  {
    "name": "2005fz",
    "z": 0.12282889997,
    "d": 1671.3609954931294,
    "t": 1574
  },
  {
    "name": "1999bi",
    "z": 0.1241,
    "d": 1686.6603522072894,
    "t": 1588
  },
  {
    "name": "2005hz",
    "z": 0.128726735467,
    "d": 1712.703377637959,
    "t": 1611
  },
  {
    "name": "2005ez",
    "z": 0.129278206634,
    "d": 1754.789987215356,
    "t": 1648
  },
  {
    "name": "2005ei",
    "z": 0.12668798909,
    "d": 1756.563793252414,
    "t": 1650
  },
  {
    "name": "1999bn",
    "z": 0.1299,
    "d": 1803.9437444043529,
    "t": 1692
  },
  {
    "name": "2005ln",
    "z": 0.145668547261,
    "d": 1843.7840562206413,
    "t": 1727
  },
  {
    "name": "1996ab",
    "z": 0.1244,
    "d": 1868.3695047562537,
    "t": 1748
  },
  {
    "name": "2005fw",
    "z": 0.1424046524,
    "d": 1900.6466828782281,
    "t": 1776
  },
  {
    "name": "2005fm",
    "z": 0.151857894665,
    "d": 1919.484782565049,
    "t": 1793
  },
  {
    "name": "2005ld",
    "z": 0.143705907,
    "d": 1960.0433270490748,
    "t": 1828
  },
  {
    "name": "1999ar",
    "z": 0.1561,
    "d": 1978.25060917175,
    "t": 1844
  },
  {
    "name": "1997i",
    "z": 0.172,
    "d": 2018.103773502485,
    "t": 1879
  },
  {
    "name": "2005fj",
    "z": 0.141787999126,
    "d": 2044.5733583703663,
    "t": 1902
  },
  {
    "name": "2005fa",
    "z": 0.160861854636,
    "d": 2053.4330229924462,
    "t": 1909
  },
  {
    "name": "2005gx",
    "z": 0.144621085972,
    "d": 2055.5598077116333,
    "t": 1911
  },
  {
    "name": "4064",
    "z": 0.155247328221,
    "d": 2061.650355623,
    "t": 1917
  },
  {
    "name": "2005ey",
    "z": 0.147025138268,
    "d": 2063.335081283208,
    "t": 1918
  },
  {
    "name": "2005hy",
    "z": 0.154632097239,
    "d": 2069.056378396268,
    "t": 1923
  },
  {
    "name": "2005gd",
    "z": 0.159889937748,
    "d": 2085.0958757007006,
    "t": 1937
  },
  {
    "name": "2005gc",
    "z": 0.163795894987,
    "d": 2120.6143506792946,
    "t": 1967
  },
  {
    "name": "e020",
    "z": 0.159,
    "d": 2150.8755758020843,
    "t": 1993
  },
  {
    "name": "1999dr",
    "z": 0.178,
    "d": 2153.9656770266447,
    "t": 1996
  },
  {
    "name": "2005is",
    "z": 0.170628396749,
    "d": 2187.6954985497173,
    "t": 2025
  },
  {
    "name": "2005ga",
    "z": 0.172742230556,
    "d": 2212.1296096447377,
    "t": 2046
  },
  {
    "name": "2005hp",
    "z": 0.173910056566,
    "d": 2239.6456078147194,
    "t": 2070
  },
  {
    "name": "2005gj",
    "z": 0.18221823956,
    "d": 2288.1896569179353,
    "t": 2111
  },
  {
    "name": "10106",
    "z": 0.146290296068,
    "d": 2322.3795507177892,
    "t": 2140
  },
  {
    "name": "2005ft",
    "z": 0.180119779968,
    "d": 2339.997298125417,
    "t": 2155
  },
  {
    "name": "k429",
    "z": 0.181,
    "d": 2386.4575341206346,
    "t": 2195
  },
  {
    "name": "1999dv",
    "z": 0.186,
    "d": 2408.6561202214166,
    "t": 2213
  },
  {
    "name": "2005ko",
    "z": 0.183568404877,
    "d": 2412.0799700753505,
    "t": 2216
  },
  {
    "name": "2005jl",
    "z": 0.17968564077,
    "d": 2431.373062144921,
    "t": 2233
  },
  {
    "name": "2005jk",
    "z": 0.188853175387,
    "d": 2492.901850705094,
    "t": 2284
  },
  {
    "name": "2005id",
    "z": 0.182548913397,
    "d": 2496.9572342689667,
    "t": 2288
  },
  {
    "name": "2005ht",
    "z": 0.18581244671,
    "d": 2536.468172732346,
    "t": 2321
  },
  {
    "name": "2005iz",
    "z": 0.200611719928,
    "d": 2538.0588671283444,
    "t": 2322
  },
  {
    "name": "d086",
    "z": 0.205,
    "d": 2589.361848888347,
    "t": 2365
  },
  {
    "name": "2005kn",
    "z": 0.196716068579,
    "d": 2632.196202217979,
    "t": 2401
  },
  {
    "name": "2005eg",
    "z": 0.189706566951,
    "d": 2666.235755640509,
    "t": 2430
  },
  {
    "name": "2005jc",
    "z": 0.211629598493,
    "d": 2667.331421479614,
    "t": 2430
  },
  {
    "name": "2005jm",
    "z": 0.202608679897,
    "d": 2672.104398342674,
    "t": 2434
  },
  {
    "name": "2005jp",
    "z": 0.210938395061,
    "d": 2673.5690320808058,
    "t": 2436
  },
  {
    "name": "2005fy",
    "z": 0.194316512142,
    "d": 2682.93701017544,
    "t": 2443
  },
  {
    "name": "2005ge",
    "z": 0.204979685349,
    "d": 2737.450196063715,
    "t": 2489
  },
  {
    "name": "g005",
    "z": 0.218,
    "d": 2772.426879591415,
    "t": 2518
  },
  {
    "name": "2005fu",
    "z": 0.192149980044,
    "d": 2785.7271999024415,
    "t": 2529
  },
  {
    "name": "2005ll",
    "z": 0.242504680476,
    "d": 2787.5148021669615,
    "t": 2530
  },
  {
    "name": "2005mi",
    "z": 0.212548765094,
    "d": 2800.562999421218,
    "t": 2541
  },
  {
    "name": "h363",
    "z": 0.213,
    "d": 2827.309448965274,
    "t": 2563
  },
  {
    "name": "2005hv",
    "z": 0.177600694977,
    "d": 2861.2975420180073,
    "t": 2591
  },
  {
    "name": "2005gr",
    "z": 0.244378876797,
    "d": 2876.4667169066433,
    "t": 2603
  },
  {
    "name": "2005fl",
    "z": 0.232781107182,
    "d": 2907.0048269646272,
    "t": 2628
  },
  {
    "name": "2005hu",
    "z": 0.218585189041,
    "d": 2933.5230223155268,
    "t": 2650
  },
  {
    "name": "2005ji",
    "z": 0.214568258658,
    "d": 2946.9577596233357,
    "t": 2661
  },
  {
    "name": "2005gf",
    "z": 0.248508130676,
    "d": 2961.2117684159243,
    "t": 2673
  },
  {
    "name": "2005jo",
    "z": 0.218347445403,
    "d": 2963.6350021868125,
    "t": 2675
  },
  {
    "name": "e132",
    "z": 0.239,
    "d": 2966.0628849810582,
    "t": 2677
  },
  {
    "name": "2005gg",
    "z": 0.228528473881,
    "d": 2984.8836418825204,
    "t": 2692
  },
  {
    "name": "1997n",
    "z": 0.18,
    "d": 3016.111279466978,
    "t": 2718
  },
  {
    "name": "2005fe",
    "z": 0.215543320953,
    "d": 3075.8230575638986,
    "t": 2766
  },
  {
    "name": "m043",
    "z": 0.266,
    "d": 3084.137112911627,
    "t": 2773
  },
  {
    "name": "2005lh",
    "z": 0.216582821954,
    "d": 3164.7438569336027,
    "t": 2838
  },
  {
    "name": "1999dy",
    "z": 0.215,
    "d": 3194.92863354804,
    "t": 2862
  },
  {
    "name": "2005ig",
    "z": 0.27945473261,
    "d": 3211.1297422228813,
    "t": 2875
  },
  {
    "name": "n404",
    "z": 0.216,
    "d": 3232.0205882419828,
    "t": 2892
  },
  {
    "name": "2005ix",
    "z": 0.265762479518,
    "d": 3241.1838876493625,
    "t": 2900
  },
  {
    "name": "2005li",
    "z": 0.255490620022,
    "d": 3249.3863946558126,
    "t": 2906
  },
  {
    "name": "k396",
    "z": 0.271,
    "d": 3278.9951056541613,
    "t": 2930
  },
  {
    "name": "2005fd",
    "z": 0.260586108317,
    "d": 3292.205404633806,
    "t": 2941
  },
  {
    "name": "2005le",
    "z": 0.252486060029,
    "d": 3306.261652233341,
    "t": 2952
  },
  {
    "name": "1999fw",
    "z": 0.278,
    "d": 3312.4029668434196,
    "t": 2957
  },
  {
    "name": "2005go",
    "z": 0.263647950642,
    "d": 3322.2701274538103,
    "t": 2965
  },
  {
    "name": "2005jz",
    "z": 0.251740186424,
    "d": 3343.92140749004,
    "t": 2982
  },
  {
    "name": "2005ih",
    "z": 0.257497888297,
    "d": 3409.9778592518387,
    "t": 3034
  },
  {
    "name": "2005jb",
    "z": 0.256475742725,
    "d": 3439.066520863689,
    "t": 3058
  },
  {
    "name": "04D3ez",
    "z": 0.263,
    "d": 3459.0511017634194,
    "t": 3073
  },
  {
    "name": "03D3bh",
    "z": 0.2486,
    "d": 3461.3031918930783,
    "t": 3075
  },
  {
    "name": "2002kc",
    "z": 0.216,
    "d": 3464.987319827229,
    "t": 3078
  },
  {
    "name": "2005fp",
    "z": 0.2115869815,
    "d": 3484.4645073490237,
    "t": 3094
  },
  {
    "name": "2005ju",
    "z": 0.258028270562,
    "d": 3488.761471244475,
    "t": 3097
  },
  {
    "name": "2005jy",
    "z": 0.270434442827,
    "d": 3493.5777474124257,
    "t": 3101
  },
  {
    "name": "2005gh",
    "z": 0.257740303509,
    "d": 3500.5042251185337,
    "t": 3106
  },
  {
    "name": "k425",
    "z": 0.274,
    "d": 3574.263831000819,
    "t": 3164
  },
  {
    "name": "2005mo",
    "z": 0.273454768884,
    "d": 3579.9258357255917,
    "t": 3169
  },
  {
    "name": "2005lo",
    "z": 0.297518833561,
    "d": 3587.180558962806,
    "t": 3175
  },
  {
    "name": "2005gw",
    "z": 0.275440197435,
    "d": 3601.1744894615535,
    "t": 3186
  },
  {
    "name": "2005ie",
    "z": 0.278924676328,
    "d": 3632.008790761727,
    "t": 3210
  },
  {
    "name": "1999dx",
    "z": 0.269,
    "d": 3674.4862711979094,
    "t": 3243
  },
  {
    "name": "2005fi",
    "z": 0.263491026592,
    "d": 3675.5155520875373,
    "t": 3244
  },
  {
    "name": "2005ia",
    "z": 0.25066763111,
    "d": 3676.2462987730223,
    "t": 3244
  },
  {
    "name": "1995ao",
    "z": 0.24,
    "d": 3702.052181937132,
    "t": 3265
  },
  {
    "name": "n278",
    "z": 0.309,
    "d": 3703.7459308695084,
    "t": 3266
  },
  {
    "name": "2005hs",
    "z": 0.300312695802,
    "d": 3704.6547484878706,
    "t": 3267
  },
  {
    "name": "03D3ba",
    "z": 0.2912,
    "d": 3717.450916445654,
    "t": 3277
  },
  {
    "name": "2005fx",
    "z": 0.288418344585,
    "d": 3731.8663072812637,
    "t": 3288
  },
  {
    "name": "p455",
    "z": 0.284,
    "d": 3731.9635891527873,
    "t": 3288
  },
  {
    "name": "2005gs",
    "z": 0.249511054792,
    "d": 3739.991960407393,
    "t": 3294
  },
  {
    "name": "2005fo",
    "z": 0.260533476953,
    "d": 3754.0352741952397,
    "t": 3305
  },
  {
    "name": "2005gt",
    "z": 0.277853422619,
    "d": 3754.4519856237457,
    "t": 3306
  },
  {
    "name": "03D4ag",
    "z": 0.285,
    "d": 3761.590125944227,
    "t": 3311
  },
  {
    "name": "1999du",
    "z": 0.26,
    "d": 3782.0608671125074,
    "t": 3327
  },
  {
    "name": "2005it",
    "z": 0.308580866071,
    "d": 3785.730379085494,
    "t": 3330
  },
  {
    "name": "m193",
    "z": 0.341,
    "d": 3839.7230323996123,
    "t": 3372
  },
  {
    "name": "2005ja",
    "z": 0.326396483203,
    "d": 3847.807868089261,
    "t": 3378
  },
  {
    "name": "2005ii",
    "z": 0.292469756082,
    "d": 3853.144057889252,
    "t": 3382
  },
  {
    "name": "1996j",
    "z": 0.3,
    "d": 3908.783199849923,
    "t": 3425
  },
  {
    "name": "2005jd",
    "z": 0.312883364158,
    "d": 3963.597218627994,
    "t": 3467
  },
  {
    "name": "2005gy",
    "z": 0.33063462833,
    "d": 3979.4134309190526,
    "t": 3480
  },
  {
    "name": "2005ic",
    "z": 0.309492645411,
    "d": 3980.7172970058873,
    "t": 3481
  },
  {
    "name": "1994g",
    "z": 0.425,
    "d": 3981.413503595884,
    "t": 3481
  },
  {
    "name": "g097",
    "z": 0.34,
    "d": 4002.4854095091796,
    "t": 3497
  },
  {
    "name": "2001iw",
    "z": 0.3396,
    "d": 4010.933326329308,
    "t": 3504
  },
  {
    "name": "03D1fc",
    "z": 0.331,
    "d": 4026.631247469293,
    "t": 3516
  },
  {
    "name": "2005jg",
    "z": 0.30240162108,
    "d": 4030.1480116037706,
    "t": 3519
  },
  {
    "name": "2005iv",
    "z": 0.298777444088,
    "d": 4034.249590850883,
    "t": 3522
  },
  {
    "name": "2005jt",
    "z": 0.360034211989,
    "d": 4086.3556184074455,
    "t": 3562
  },
  {
    "name": "2005fr",
    "z": 0.286618706522,
    "d": 4089.380980703037,
    "t": 3564
  },
  {
    "name": "2005lf",
    "z": 0.29840927363,
    "d": 4097.267727052226,
    "t": 3570
  },
  {
    "name": "2005jn",
    "z": 0.320446988861,
    "d": 4104.516079212064,
    "t": 3575
  },
  {
    "name": "h364",
    "z": 0.344,
    "d": 4164.864335797458,
    "t": 3621
  },
  {
    "name": "1996e",
    "z": 0.43,
    "d": 4186.600314322219,
    "t": 3638
  },
  {
    "name": "1166",
    "z": 0.380416514286,
    "d": 4245.060309426355,
    "t": 3682
  },
  {
    "name": "2005fc",
    "z": 0.295585550063,
    "d": 4249.831876181775,
    "t": 3686
  },
  {
    "name": "d087",
    "z": 0.34,
    "d": 4255.561400983942,
    "t": 3690
  },
  {
    "name": "d117",
    "z": 0.309,
    "d": 4278.04550851614,
    "t": 3707
  },
  {
    "name": "f076",
    "z": 0.41,
    "d": 4302.347227697731,
    "t": 3726
  },
  {
    "name": "2005ik",
    "z": 0.309547337158,
    "d": 4313.363389345873,
    "t": 3734
  },
  {
    "name": "2005gu",
    "z": 0.330512448683,
    "d": 4315.138732684999,
    "t": 3735
  },
  {
    "name": "e029",
    "z": 0.332,
    "d": 4365.332615871879,
    "t": 3773
  },
  {
    "name": "m062",
    "z": 0.314,
    "d": 4377.479760288577,
    "t": 3782
  },
  {
    "name": "1997ac",
    "z": 0.32,
    "d": 4383.012043483984,
    "t": 3786
  },
  {
    "name": "2005lg",
    "z": 0.348583857544,
    "d": 4402.8729661574735,
    "t": 3801
  },
  {
    "name": "2005mq",
    "z": 0.348345020835,
    "d": 4417.567308656645,
    "t": 3812
  },
  {
    "name": "04D3kr",
    "z": 0.3373,
    "d": 4426.854527416124,
    "t": 3819
  },
  {
    "name": "m027",
    "z": 0.286,
    "d": 4430.0752678266135,
    "t": 3822
  },
  {
    "name": "1688",
    "z": 0.357507357032,
    "d": 4430.488298312288,
    "t": 3822
  },
  {
    "name": "2005fs",
    "z": 0.338802609134,
    "d": 4444.099059330905,
    "t": 3832
  },
  {
    "name": "f096",
    "z": 0.412,
    "d": 4449.729857733273,
    "t": 3836
  },
  {
    "name": "1998as",
    "z": 0.355,
    "d": 4466.310629876667,
    "t": 3849
  },
  {
    "name": "04D3nh",
    "z": 0.3402,
    "d": 4486.158327587777,
    "t": 3864
  },
  {
    "name": "2005gv",
    "z": 0.361934308832,
    "d": 4530.648969843029,
    "t": 3897
  },
  {
    "name": "03D1bp",
    "z": 0.346,
    "d": 4542.617998337042,
    "t": 3906
  },
  {
    "name": "b016",
    "z": 0.329,
    "d": 4549.380581816151,
    "t": 3911
  },
  {
    "name": "2005jw",
    "z": 0.379662293575,
    "d": 4573.6769746557375,
    "t": 3929
  },
  {
    "name": "g055",
    "z": 0.302,
    "d": 4581.150691468044,
    "t": 3934
  },
  {
    "name": "d149",
    "z": 0.342,
    "d": 4598.254710419451,
    "t": 3947
  },
  {
    "name": "g142",
    "z": 0.399,
    "d": 4626.20147253712,
    "t": 3968
  },
  {
    "name": "04D2fs",
    "z": 0.357,
    "d": 4633.953271109554,
    "t": 3973
  },
  {
    "name": "2001iv",
    "z": 0.3965,
    "d": 4634.1397102779465,
    "t": 3974
  },
  {
    "name": "e136",
    "z": 0.352,
    "d": 4647.346816396719,
    "t": 3983
  },
  {
    "name": "04D3fk",
    "z": 0.3578,
    "d": 4651.275020451268,
    "t": 3986
  },
  {
    "name": "n263",
    "z": 0.368,
    "d": 4686.8262638190345,
    "t": 4013
  },
  {
    "name": "5737",
    "z": 0.391599213441,
    "d": 4695.233019487868,
    "t": 4019
  },
  {
    "name": "2005ka",
    "z": 0.316429844695,
    "d": 4710.238103996972,
    "t": 4030
  },
  {
    "name": "2002ab",
    "z": 0.423,
    "d": 4713.311913921808,
    "t": 4032
  },
  {
    "name": "k485",
    "z": 0.416,
    "d": 4719.218013258138,
    "t": 4036
  },
  {
    "name": "d093",
    "z": 0.363,
    "d": 4890.183840989962,
    "t": 4162
  },
  {
    "name": "2005lq",
    "z": 0.378965802039,
    "d": 4899.707893492007,
    "t": 4169
  },
  {
    "name": "2005gq",
    "z": 0.389288787688,
    "d": 4910.877036049997,
    "t": 4177
  },
  {
    "name": "2005lp",
    "z": 0.301755029535,
    "d": 4984.926275977807,
    "t": 4231
  },
  {
    "name": "1996cg",
    "z": 0.49,
    "d": 4985.705528560254,
    "t": 4231
  },
  {
    "name": "g052",
    "z": 0.383,
    "d": 5023.547412758641,
    "t": 4259
  },
  {
    "name": "h359",
    "z": 0.348,
    "d": 5031.080342611477,
    "t": 4264
  },
  {
    "name": "04D2cf",
    "z": 0.369,
    "d": 5056.232779338119,
    "t": 4283
  },
  {
    "name": "2005mm",
    "z": 0.380359487336,
    "d": 5069.130036235441,
    "t": 4292
  },
  {
    "name": "d085",
    "z": 0.401,
    "d": 5082.444708416808,
    "t": 4302
  },
  {
    "name": "f235",
    "z": 0.422,
    "d": 5083.796994118161,
    "t": 4303
  },
  {
    "name": "03D3ay",
    "z": 0.3709,
    "d": 5131.697029306429,
    "t": 4337
  },
  {
    "name": "g120",
    "z": 0.51,
    "d": 5135.53899629011,
    "t": 4340
  },
  {
    "name": "04D3gt",
    "z": 0.451,
    "d": 5141.541852512705,
    "t": 4344
  },
  {
    "name": "1997q",
    "z": 0.43,
    "d": 5144.192753849708,
    "t": 4346
  },
  {
    "name": "b013",
    "z": 0.426,
    "d": 5147.802486069565,
    "t": 4349
  },
  {
    "name": "1995ar",
    "z": 0.465,
    "d": 5159.658290968928,
    "t": 4357
  },
  {
    "name": "2005hq",
    "z": 0.399601334976,
    "d": 5166.323766879643,
    "t": 4362
  },
  {
    "name": "1997ai",
    "z": 0.45,
    "d": 5229.453101629605,
    "t": 4407
  },
  {
    "name": "1996cn",
    "z": 0.43,
    "d": 5229.703738409603,
    "t": 4407
  },
  {
    "name": "04D2gb",
    "z": 0.43,
    "d": 5251.387026079401,
    "t": 4423
  },
  {
    "name": "1997h",
    "z": 0.526,
    "d": 5261.233093856721,
    "t": 4430
  },
  {
    "name": "2005mh",
    "z": 0.393974478272,
    "d": 5313.7579389991915,
    "t": 4468
  },
  {
    "name": "1997aj",
    "z": 0.581,
    "d": 5335.543813836081,
    "t": 4483
  },
  {
    "name": "d089",
    "z": 0.436,
    "d": 5398.519878968878,
    "t": 4528
  },
  {
    "name": "2005hw",
    "z": 0.408319092164,
    "d": 5404.848725714562,
    "t": 4532
  },
  {
    "name": "e148",
    "z": 0.429,
    "d": 5450.061946076342,
    "t": 4564
  },
  {
    "name": "m158",
    "z": 0.463,
    "d": 5466.7892224583575,
    "t": 4576
  },
  {
    "name": "04D2fp",
    "z": 0.415,
    "d": 5470.456360454138,
    "t": 4579
  },
  {
    "name": "1997p",
    "z": 0.472,
    "d": 5487.199447967903,
    "t": 4591
  },
  {
    "name": "g050",
    "z": 0.633,
    "d": 5505.214140052093,
    "t": 4603
  },
  {
    "name": "d097",
    "z": 0.436,
    "d": 5513.473925225951,
    "t": 4609
  },
  {
    "name": "2005iy",
    "z": 0.402459619216,
    "d": 5607.443300227848,
    "t": 4675
  },
  {
    "name": "2005kq",
    "z": 0.387297107465,
    "d": 5620.170486082096,
    "t": 4684
  },
  {
    "name": "2005jj",
    "z": 0.366602898789,
    "d": 5620.241976700987,
    "t": 4684
  },
  {
    "name": "e149",
    "z": 0.497,
    "d": 5667.0737908439205,
    "t": 4717
  },
  {
    "name": "k448",
    "z": 0.401,
    "d": 5676.939059567276,
    "t": 4724
  },
  {
    "name": "1999fn",
    "z": 0.477,
    "d": 5687.382543392909,
    "t": 4732
  },
  {
    "name": "03D3cc",
    "z": 0.4627,
    "d": 5711.203600321536,
    "t": 4748
  },
  {
    "name": "03D3aw",
    "z": 0.449,
    "d": 5714.407265959265,
    "t": 4750
  },
  {
    "name": "1998aw",
    "z": 0.44,
    "d": 5717.325515013811,
    "t": 4752
  },
  {
    "name": "1995at",
    "z": 0.655,
    "d": 5723.279512316928,
    "t": 4757
  },
  {
    "name": "1996ci",
    "z": 0.495,
    "d": 5788.504069900339,
    "t": 4802
  },
  {
    "name": "03D3cd",
    "z": 0.4607,
    "d": 5796.931718322562,
    "t": 4808
  },
  {
    "name": "1997ce",
    "z": 0.44,
    "d": 5820.630993675468,
    "t": 4824
  },
  {
    "name": "2002dc",
    "z": 0.475,
    "d": 5829.21622610644,
    "t": 4830
  },
  {
    "name": "04D2gc",
    "z": 0.521,
    "d": 5852.246104831168,
    "t": 4846
  },
  {
    "name": "g160",
    "z": 0.493,
    "d": 5871.499538139216,
    "t": 4860
  },
  {
    "name": "f011",
    "z": 0.539,
    "d": 5909.080775814792,
    "t": 4886
  },
  {
    "name": "04D3df",
    "z": 0.47,
    "d": 5929.532684344752,
    "t": 4900
  },
  {
    "name": "p524",
    "z": 0.508,
    "d": 5941.262071775326,
    "t": 4908
  },
  {
    "name": "1995ay",
    "z": 0.48,
    "d": 5958.73275428414,
    "t": 4920
  },
  {
    "name": "e140",
    "z": 0.631,
    "d": 5976.522626256785,
    "t": 4932
  },
  {
    "name": "04D4bq",
    "z": 0.55,
    "d": 6000.999851098298,
    "t": 4949
  },
  {
    "name": "04Yow",
    "z": 0.46,
    "d": 6008.4571922973155,
    "t": 4954
  },
  {
    "name": "03D1ax",
    "z": 0.496,
    "d": 6045.462298536736,
    "t": 4980
  },
  {
    "name": "03D1gt",
    "z": 0.548,
    "d": 6066.171157398018,
    "t": 4994
  },
  {
    "name": "1997ck",
    "z": 0.97,
    "d": 6070.164286260438,
    "t": 4997
  },
  {
    "name": "04D3hn",
    "z": 0.5516,
    "d": 6071.316600869784,
    "t": 4997
  },
  {
    "name": "1996k",
    "z": 0.38,
    "d": 6111.9828264151165,
    "t": 5025
  },
  {
    "name": "2005jv",
    "z": 0.420926821103,
    "d": 6131.458510412078,
    "t": 5038
  },
  {
    "name": "g133",
    "z": 0.421,
    "d": 6138.1592672697325,
    "t": 5043
  },
  {
    "name": "h319",
    "z": 0.495,
    "d": 6144.936305136982,
    "t": 5048
  },
  {
    "name": "k411",
    "z": 0.564,
    "d": 6219.672336438169,
    "t": 5099
  },
  {
    "name": "d058",
    "z": 0.583,
    "d": 6225.440163342955,
    "t": 5103
  },
  {
    "name": "1998ba",
    "z": 0.43,
    "d": 6236.123516061982,
    "t": 5110
  },
  {
    "name": "h342",
    "z": 0.421,
    "d": 6262.638992993263,
    "t": 5128
  },
  {
    "name": "03D4gl",
    "z": 0.571,
    "d": 6267.32380065384,
    "t": 5131
  },
  {
    "name": "1998ax",
    "z": 0.497,
    "d": 6354.987821131386,
    "t": 5190
  },
  {
    "name": "n285",
    "z": 0.528,
    "d": 6356.83470765903,
    "t": 5192
  },
  {
    "name": "03D1au",
    "z": 0.5043,
    "d": 6364.020770999882,
    "t": 5196
  },
  {
    "name": "Z-005",
    "z": 0.623,
    "d": 6397.527840585264,
    "t": 5219
  },
  {
    "name": "1996cm",
    "z": 0.45,
    "d": 6401.069432278663,
    "t": 5221
  },
  {
    "name": "05Zwi",
    "z": 0.521,
    "d": 6411.292664408573,
    "t": 5228
  },
  {
    "name": "2001gy",
    "z": 0.511,
    "d": 6440.113685744996,
    "t": 5248
  },
  {
    "name": "04D1ak",
    "z": 0.526,
    "d": 6455.256552010669,
    "t": 5258
  },
  {
    "name": "1997cj",
    "z": 0.5,
    "d": 6455.580458543347,
    "t": 5258
  },
  {
    "name": "1997eq",
    "z": 0.54,
    "d": 6468.885102842205,
    "t": 5267
  },
  {
    "name": "1995ba",
    "z": 0.388,
    "d": 6494.702257053756,
    "t": 5284
  },
  {
    "name": "03D4dy",
    "z": 0.604,
    "d": 6510.537386021159,
    "t": 5295
  },
  {
    "name": "1995ax",
    "z": 0.615,
    "d": 6512.994325823891,
    "t": 5297
  },
  {
    "name": "1995k",
    "z": 0.479,
    "d": 6513.4229998340825,
    "t": 5297
  },
  {
    "name": "1996i",
    "z": 0.57,
    "d": 6536.546037323486,
    "t": 5312
  },
  {
    "name": "1999ff",
    "z": 0.455,
    "d": 6536.561715729488,
    "t": 5312
  },
  {
    "name": "e108",
    "z": 0.469,
    "d": 6565.992031454678,
    "t": 5332
  },
  {
    "name": "2001jp",
    "z": 0.528,
    "d": 6609.5587085235775,
    "t": 5361
  },
  {
    "name": "2000fr",
    "z": 0.543,
    "d": 6619.438459862932,
    "t": 5368
  },
  {
    "name": "2001go",
    "z": 0.552,
    "d": 6679.147635296296,
    "t": 5408
  },
  {
    "name": "03D4gg",
    "z": 0.592,
    "d": 6713.47527565208,
    "t": 5430
  },
  {
    "name": "f244",
    "z": 0.54,
    "d": 6731.903591584168,
    "t": 5443
  },
  {
    "name": "p534",
    "z": 0.613,
    "d": 6747.353383419106,
    "t": 5453
  },
  {
    "name": "1995aw",
    "z": 0.4,
    "d": 6758.515294253765,
    "t": 5460
  },
  {
    "name": "04D1ag",
    "z": 0.557,
    "d": 6800.479454244986,
    "t": 5488
  },
  {
    "name": "1995az",
    "z": 0.45,
    "d": 6800.603391860911,
    "t": 5488
  },
  {
    "name": "h323",
    "z": 0.603,
    "d": 6882.295629977225,
    "t": 5542
  },
  {
    "name": "1996u",
    "z": 0.43,
    "d": 6883.3233089133255,
    "t": 5543
  },
  {
    "name": "03D3af",
    "z": 0.532,
    "d": 6939.533418182104,
    "t": 5579
  },
  {
    "name": "1997am",
    "z": 0.416,
    "d": 7032.11654292357,
    "t": 5640
  },
  {
    "name": "03D1aw",
    "z": 0.5817,
    "d": 7058.459249277996,
    "t": 5657
  },
  {
    "name": "1998be",
    "z": 0.64,
    "d": 7102.831496034202,
    "t": 5686
  },
  {
    "name": "1996cf",
    "z": 0.57,
    "d": 7109.18138352414,
    "t": 5690
  },
  {
    "name": "h300",
    "z": 0.687,
    "d": 7133.0923482615035,
    "t": 5706
  },
  {
    "name": "03D4dh",
    "z": 0.6268,
    "d": 7141.908210350844,
    "t": 5712
  },
  {
    "name": "03D4au",
    "z": 0.468,
    "d": 7185.890527552173,
    "t": 5740
  },
  {
    "name": "f216",
    "z": 0.599,
    "d": 7215.56628023543,
    "t": 5759
  },
  {
    "name": "2001iy",
    "z": 0.568,
    "d": 7243.188224626944,
    "t": 5777
  },
  {
    "name": "e147",
    "z": 0.645,
    "d": 7255.287654497566,
    "t": 5785
  },
  {
    "name": "03D4gf",
    "z": 0.581,
    "d": 7293.881496567251,
    "t": 5810
  },
  {
    "name": "n258",
    "z": 0.522,
    "d": 7353.215970349135,
    "t": 5848
  },
  {
    "name": "e138",
    "z": 0.612,
    "d": 7393.482618364452,
    "t": 5874
  },
  {
    "name": "k441",
    "z": 0.68,
    "d": 7394.75031739922,
    "t": 5875
  },
  {
    "name": "n256",
    "z": 0.631,
    "d": 7539.403771449569,
    "t": 5967
  },
  {
    "name": "f308",
    "z": 0.401,
    "d": 7549.389654356996,
    "t": 5974
  },
  {
    "name": "2003be",
    "z": 0.64,
    "d": 7646.050174083165,
    "t": 6035
  },
  {
    "name": "04D3is",
    "z": 0.71,
    "d": 7670.7451906545,
    "t": 6051
  },
  {
    "name": "g240",
    "z": 0.687,
    "d": 7684.008524550086,
    "t": 6059
  },
  {
    "name": "2001gq",
    "z": 0.671,
    "d": 7706.38771945458,
    "t": 6073
  },
  {
    "name": "04D3do",
    "z": 0.61,
    "d": 7719.571094299222,
    "t": 6081
  },
  {
    "name": "2001kd",
    "z": 0.936,
    "d": 7725.769106420632,
    "t": 6085
  },
  {
    "name": "1997r",
    "z": 0.657,
    "d": 7747.349348934272,
    "t": 6099
  },
  {
    "name": "2002ad",
    "z": 0.514,
    "d": 7772.10669571242,
    "t": 6115
  },
  {
    "name": "2002kd",
    "z": 0.735,
    "d": 7807.185464378611,
    "t": 6137
  },
  {
    "name": "f041",
    "z": 0.561,
    "d": 7841.751617096122,
    "t": 6158
  },
  {
    "name": "03D1fl",
    "z": 0.688,
    "d": 7885.88917761922,
    "t": 6186
  },
  {
    "name": "2001fs",
    "z": 0.874,
    "d": 7938.385160905651,
    "t": 6219
  },
  {
    "name": "04D3cy",
    "z": 0.643,
    "d": 7944.045793455177,
    "t": 6222
  },
  {
    "name": "04D2iu",
    "z": 0.691,
    "d": 7998.999751611217,
    "t": 6257
  },
  {
    "name": "04D4an",
    "z": 0.613,
    "d": 8026.689627827195,
    "t": 6274
  },
  {
    "name": "04D3co",
    "z": 0.62,
    "d": 8049.361112847527,
    "t": 6288
  },
  {
    "name": "03D4at",
    "z": 0.633,
    "d": 8136.027843561158,
    "t": 6342
  },
  {
    "name": "03D4cx",
    "z": 0.949,
    "d": 8177.038384289243,
    "t": 6367
  },
  {
    "name": "04D1aj",
    "z": 0.721,
    "d": 8180.516238321646,
    "t": 6369
  },
  {
    "name": "2001hu",
    "z": 0.882,
    "d": 8200.004131685997,
    "t": 6381
  },
  {
    "name": "f231",
    "z": 0.619,
    "d": 8229.676872211996,
    "t": 6400
  },
  {
    "name": "1995aq",
    "z": 0.453,
    "d": 8230.040755890024,
    "t": 6400
  },
  {
    "name": "2001jm",
    "z": 0.978,
    "d": 8264.451789402437,
    "t": 6421
  },
  {
    "name": "1998bi",
    "z": 0.75,
    "d": 8298.270616675876,
    "t": 6442
  },
  {
    "name": "2003bd",
    "z": 0.67,
    "d": 8305.223889105997,
    "t": 6446
  },
  {
    "name": "1996ck",
    "z": 0.656,
    "d": 8381.801925880407,
    "t": 6493
  },
  {
    "name": "03D4cz",
    "z": 0.695,
    "d": 8444.949453455692,
    "t": 6532
  },
  {
    "name": "05Spo",
    "z": 0.839,
    "d": 8481.200306740275,
    "t": 6554
  },
  {
    "name": "04D3ny",
    "z": 0.81,
    "d": 8506.008824443012,
    "t": 6569
  },
  {
    "name": "m034",
    "z": 0.562,
    "d": 8508.429295296866,
    "t": 6570
  },
  {
    "name": "04D3ks",
    "z": 0.752,
    "d": 8516.433882783402,
    "t": 6575
  },
  {
    "name": "04Rak",
    "z": 0.74,
    "d": 8518.94858957103,
    "t": 6577
  },
  {
    "name": "04D3fq",
    "z": 0.73,
    "d": 8526.659212437766,
    "t": 6582
  },
  {
    "name": "1998ay",
    "z": 0.64,
    "d": 8540.006388931999,
    "t": 6590
  },
  {
    "name": "03D4cn",
    "z": 0.818,
    "d": 8558.760238691042,
    "t": 6601
  },
  {
    "name": "2001hx",
    "z": 0.799,
    "d": 8593.31282142678,
    "t": 6622
  },
  {
    "name": "1995as",
    "z": 0.498,
    "d": 8603.162754146357,
    "t": 6628
  },
  {
    "name": "2003XX",
    "z": 0.935,
    "d": 8605.66394539972,
    "t": 6629
  },
  {
    "name": "04D4dm",
    "z": 0.811,
    "d": 8638.029022641207,
    "t": 6649
  },
  {
    "name": "04D2gp",
    "z": 0.707,
    "d": 8663.18338513201,
    "t": 6664
  },
  {
    "name": "04D3ki",
    "z": 0.93,
    "d": 8676.698595246,
    "t": 6672
  },
  {
    "name": "03D1ew",
    "z": 0.868,
    "d": 8723.816345631287,
    "t": 6701
  },
  {
    "name": "04D3nr",
    "z": 0.96,
    "d": 8786.423965596287,
    "t": 6739
  },
  {
    "name": "H-003",
    "z": 0.85,
    "d": 8812.632212042548,
    "t": 6754
  },
  {
    "name": "d084",
    "z": 0.519,
    "d": 8834.257905636574,
    "t": 6767
  },
  {
    "name": "k430",
    "z": 0.582,
    "d": 8851.186199574713,
    "t": 6777
  },
  {
    "name": "1996h",
    "z": 0.62,
    "d": 8902.321921874087,
    "t": 6808
  },
  {
    "name": "p528",
    "z": 0.781,
    "d": 8916.776799321267,
    "t": 6817
  },
  {
    "name": "1999fm",
    "z": 0.95,
    "d": 8934.182405108959,
    "t": 6827
  },
  {
    "name": "2003eq",
    "z": 0.84,
    "d": 8942.706086270255,
    "t": 6832
  },
  {
    "name": "1997af",
    "z": 0.579,
    "d": 8960.174005943021,
    "t": 6843
  },
  {
    "name": "b010",
    "z": 0.591,
    "d": 8986.217351895668,
    "t": 6858
  },
  {
    "name": "1997ap",
    "z": 0.83,
    "d": 9108.681205295215,
    "t": 6931
  },
  {
    "name": "03D4di",
    "z": 0.905,
    "d": 9147.005202750533,
    "t": 6953
  },
  {
    "name": "2001fo",
    "z": 0.772,
    "d": 9267.464965519559,
    "t": 7024
  },
  {
    "name": "04Man",
    "z": 0.854,
    "d": 9268.490994347752,
    "t": 7025
  },
  {
    "name": "03D4fd",
    "z": 0.791,
    "d": 9455.979956314828,
    "t": 7135
  },
  {
    "name": "1997f",
    "z": 0.58,
    "d": 9457.880462714662,
    "t": 7136
  },
  {
    "name": "03D1co",
    "z": 0.679,
    "d": 9546.770375421178,
    "t": 7188
  },
  {
    "name": "P-009",
    "z": 0.821,
    "d": 9578.637027780956,
    "t": 7206
  },
  {
    "name": "1997ez",
    "z": 0.78,
    "d": 9619.82865555549,
    "t": 7230
  },
  {
    "name": "04D3nc",
    "z": 0.817,
    "d": 9646.809997494234,
    "t": 7246
  },
  {
    "name": "C-001",
    "z": 0.974,
    "d": 9658.449375848177,
    "t": 7252
  },
  {
    "name": "2001hy",
    "z": 0.812,
    "d": 9682.385430509234,
    "t": 7266
  },
  {
    "name": "2001hs",
    "z": 0.833,
    "d": 9724.852198062765,
    "t": 7291
  },
  {
    "name": "1999fj",
    "z": 0.816,
    "d": 9829.391587359334,
    "t": 7351
  },
  {
    "name": "2001ix",
    "z": 0.711,
    "d": 9851.124510780126,
    "t": 7363
  },
  {
    "name": "C-000",
    "z": 1.092,
    "d": 9872.650626463279,
    "t": 7376
  },
  {
    "name": "2002dd",
    "z": 0.95,
    "d": 10005.09812457485,
    "t": 7451
  },
  {
    "name": "03D1fq",
    "z": 0.8,
    "d": 10022.254362432544,
    "t": 7461
  },
  {
    "name": "1997o",
    "z": 0.374,
    "d": 10291.107343854632,
    "t": 7613
  },
  {
    "name": "04D3dd",
    "z": 1.01,
    "d": 10297.332936257559,
    "t": 7617
  },
  {
    "name": "04D3lu",
    "z": 0.8218,
    "d": 10375.236367858723,
    "t": 7660
  },
  {
    "name": "04D2ja",
    "z": 0.741,
    "d": 10377.137976604296,
    "t": 7661
  },
  {
    "name": "03D4cy",
    "z": 0.9271,
    "d": 10390.135892129892,
    "t": 7669
  },
  {
    "name": "04D3ml",
    "z": 0.95,
    "d": 10440.295591709579,
    "t": 7697
  },
  {
    "name": "2002ki",
    "z": 1.14,
    "d": 10529.374151032682,
    "t": 7746
  },
  {
    "name": "04D4bk",
    "z": 0.84,
    "d": 10549.423343856088,
    "t": 7758
  },
  {
    "name": "1997ek",
    "z": 0.86,
    "d": 10671.982261857118,
    "t": 7826
  },
  {
    "name": "1999fk",
    "z": 1.057,
    "d": 10723.032769860816,
    "t": 7854
  },
  {
    "name": "04D3oe",
    "z": 0.756,
    "d": 10757.214569370137,
    "t": 7873
  },
  {
    "name": "2001jb",
    "z": 0.698,
    "d": 10895.168623581494,
    "t": 7949
  },
  {
    "name": "05Fer",
    "z": 1.02,
    "d": 10987.215455237481,
    "t": 7999
  },
  {
    "name": "05Red",
    "z": 1.19,
    "d": 11105.755840031552,
    "t": 8064
  },
  {
    "name": "04D3lp",
    "z": 0.983,
    "d": 11157.32449479547,
    "t": 8092
  },
  {
    "name": "04Gre",
    "z": 1.14,
    "d": 11158.441736961639,
    "t": 8092
  },
  {
    "name": "m138",
    "z": 0.581,
    "d": 11174.548591640456,
    "t": 8101
  },
  {
    "name": "2001hb",
    "z": 1.03,
    "d": 11322.66187747715,
    "t": 8181
  },
  {
    "name": "04D3cp",
    "z": 0.83,
    "d": 11510.834289771641,
    "t": 8282
  },
  {
    "name": "2002x",
    "z": 0.859,
    "d": 11553.85826192382,
    "t": 8305
  },
  {
    "name": "A-004",
    "z": 1.192,
    "d": 11596.73345041045,
    "t": 8328
  },
  {
    "name": "D-000",
    "z": 1.017,
    "d": 11681.918199528825,
    "t": 8373
  },
  {
    "name": "2001jf",
    "z": 0.815,
    "d": 11733.55452060475,
    "t": 8401
  },
  {
    "name": "04D4dw",
    "z": 0.961,
    "d": 11851.917904820571,
    "t": 8463
  },
  {
    "name": "2001jh",
    "z": 0.885,
    "d": 11884.508116927658,
    "t": 8480
  },
  {
    "name": "2001cw",
    "z": 0.953,
    "d": 11952.19601527797,
    "t": 8516
  },
  {
    "name": "H-005",
    "z": 1.241,
    "d": 12003.96278946359,
    "t": 8543
  },
  {
    "name": "04Eag",
    "z": 1.02,
    "d": 12040.91459432917,
    "t": 8562
  },
  {
    "name": "04Omb",
    "z": 0.975,
    "d": 12150.772913822175,
    "t": 8620
  },
  {
    "name": "03D1cm",
    "z": 0.87,
    "d": 12241.79603494693,
    "t": 8667
  },
  {
    "name": "05Gab",
    "z": 1.12,
    "d": 12301.870228482014,
    "t": 8698
  },
  {
    "name": "K-000",
    "z": 1.414,
    "d": 12343.600769873687,
    "t": 8720
  },
  {
    "name": "04D3gx",
    "z": 0.91,
    "d": 12402.116946405236,
    "t": 8750
  },
  {
    "name": "N-033",
    "z": 1.188,
    "d": 12442.484178463039,
    "t": 8771
  },
  {
    "name": "2002hp",
    "z": 1.305,
    "d": 12554.194151302292,
    "t": 8828
  },
  {
    "name": "2001gn",
    "z": 1.124,
    "d": 12582.740173246346,
    "t": 8843
  },
  {
    "name": "G-004",
    "z": 1.35,
    "d": 12816.550055910518,
    "t": 8962
  },
  {
    "name": "04Sas",
    "z": 1.39,
    "d": 12890.651637215791,
    "t": 9000
  },
  {
    "name": "04Pat",
    "z": 0.97,
    "d": 12926.472250011557,
    "t": 9018
  },
  {
    "name": "F-012",
    "z": 1.11,
    "d": 13008.002749375684,
    "t": 9059
  },
  {
    "name": "1997k",
    "z": 0.592,
    "d": 13866.083354899749,
    "t": 9485
  },
  {
    "name": "D-006",
    "z": 1.315,
    "d": 13904.214672852619,
    "t": 9504
  },
  {
    "name": "2003az",
    "z": 1.265,
    "d": 14033.94812044912,
    "t": 9567
  },
  {
    "name": "04Mcg",
    "z": 1.37,
    "d": 14080.569763198882,
    "t": 9589
  },
  {
    "name": "2002fw",
    "z": 1.3,
    "d": 14287.284379667959,
    "t": 9689
  },
  {
    "name": "2003dy",
    "z": 1.34,
    "d": 14378.419944899231,
    "t": 9733
  },
  {
    "name": "1997g",
    "z": 0.763,
    "d": 14509.70261554138,
    "t": 9796
  },
  {
    "name": "05Lan",
    "z": 1.23,
    "d": 14765.772960330058,
    "t": 9917
  },
  {
    "name": "1997l",
    "z": 0.55,
    "d": 15552.05255841749,
    "t": 10284
  },
  {
    "name": "05Str",
    "z": 1.01,
    "d": 15583.227583516795,
    "t": 10298
  },
  {
    "name": "R-012",
    "z": 1.215,
    "d": 16495.153609358444,
    "t": 10710
  },
  {
    "name": "2003aj",
    "z": 1.307,
    "d": 17081.544318316344,
    "t": 10968
  }
]